Metadata-Version: 2.1
Name: lxc
Version: 3.0.4.0
Summary: Python3 bindings for LXC
Home-page: https://github.com/lxc/python3-lxc
Maintainer: lxc
Maintainer-email: lxc-devel@lists.linuxcontainers.org
License: LGPLv2+
Platform: UNKNOWN
License-File: COPYING
